fast_array_utils/__init__.py
fast_array_utils/_validation.py
fast_array_utils/py.typed
fast_array_utils/types.py
fast_array_utils/typing.py
fast_array_utils/_plugins/__init__.py
fast_array_utils/_plugins/dask.py
fast_array_utils/_plugins/numba_sparse.py
fast_array_utils/conv/__init__.py
fast_array_utils/conv/_to_dense.py
fast_array_utils/conv/scipy/__init__.py
fast_array_utils/conv/scipy/_to_dense.py
fast_array_utils/stats/__init__.py
fast_array_utils/stats/_generic_ops.py
fast_array_utils/stats/_is_constant.py
fast_array_utils/stats/_mean.py
fast_array_utils/stats/_mean_var.py
fast_array_utils/stats/_power.py
fast_array_utils/stats/_typing.py
fast_array_utils/stats/_utils.py
testing/fast_array_utils/__init__.py
testing/fast_array_utils/_array_type.py
testing/fast_array_utils/pytest.py
fast_array_utils-1.3.1.dist-info/METADATA
fast_array_utils-1.3.1.dist-info/WHEEL
fast_array_utils-1.3.1.dist-info/entry_points.txt
fast_array_utils-1.3.1.dist-info/licenses/LICENSE.rst
fast_array_utils-1.3.1.dist-info/RECORD
