Metadata-Version: 2.4
Name: fast-array-utils
Version: 1.3.1
Summary: Fast array utilities with minimal dependencies.
Project-URL: Documentation, https://icb-fast-array-utils.readthedocs-hosted.com/
Project-URL: Issue Tracker, https://github.com/scverse/fast-array-utils/issues
Project-URL: Source Code, https://github.com/scverse/fast-array-utils
Author-email: "Philipp A." <flying-sheep@web.de>
License-Expression: MPL-2.0
License-File: LICENSE.rst
Classifier: Development Status :: 5 - Production/Stable
Classifier: Intended Audience :: Developers
Classifier: Programming Language :: Python :: 3 :: Only
Classifier: Programming Language :: Python :: 3.11
Classifier: Programming Language :: Python :: 3.12
Classifier: Programming Language :: Python :: 3.13
Classifier: Programming Language :: Python :: 3.14
Requires-Python: >=3.11
Requires-Dist: numpy>=2
Provides-Extra: accel
Requires-Dist: numba>=0.57; extra == 'accel'
Provides-Extra: dask
Requires-Dist: dask>=2023.6.1; extra == 'dask'
Provides-Extra: doc
Requires-Dist: furo>=2024.8.6; extra == 'doc'
Requires-Dist: pytest>=8.4; extra == 'doc'
Requires-Dist: scanpydoc>=0.15.4; extra == 'doc'
Requires-Dist: sphinx-autodoc-typehints>=3.2; extra == 'doc'
Requires-Dist: sphinx-autofixture>=0.4.1; extra == 'doc'
Requires-Dist: sphinx>=8.2.3; extra == 'doc'
Provides-Extra: full
Requires-Dist: dask>=2023.6.1; extra == 'full'
Requires-Dist: h5py; extra == 'full'
Requires-Dist: numba>=0.57; extra == 'full'
Requires-Dist: scipy>=1.13; extra == 'full'
Requires-Dist: zarr; extra == 'full'
Provides-Extra: sparse
Requires-Dist: scipy>=1.13; extra == 'sparse'
Provides-Extra: test
Requires-Dist: anndata; extra == 'test'
Requires-Dist: coverage[toml]; extra == 'test'
Requires-Dist: numba>=0.57; extra == 'test'
Requires-Dist: numcodecs<0.16; extra == 'test'
Requires-Dist: packaging; extra == 'test'
Requires-Dist: pytest; extra == 'test'
Requires-Dist: pytest-codspeed; extra == 'test'
Requires-Dist: pytest-doctestplus; extra == 'test'
Requires-Dist: pytest-xdist; extra == 'test'
Requires-Dist: scipy>=1.13; extra == 'test'
Requires-Dist: zarr<3; extra == 'test'
Provides-Extra: test-min
Requires-Dist: coverage[toml]; extra == 'test-min'
Requires-Dist: packaging; extra == 'test-min'
Requires-Dist: pytest; extra == 'test-min'
Requires-Dist: pytest-codspeed; extra == 'test-min'
Requires-Dist: pytest-doctestplus; extra == 'test-min'
Requires-Dist: pytest-xdist; extra == 'test-min'
Requires-Dist: scipy>=1.13; extra == 'test-min'
Provides-Extra: testing
Requires-Dist: packaging; extra == 'testing'
